Metadata-Version: 2.1
Name: windy-crawler
Version: 0.21
Summary: Windy-Web-Crawler is a command line web crawler that crawls 'www.windy.com' and displays the Temperature and wind speed for next 5 days 
Home-page: UNKNOWN
Author: Ganesh Prasad B G
Author-email: gnshprasad402@gmail.com
License: Mozilla Public License Version 2.0
Platform: UNKNOWN
Classifier: Development Status :: 5 - Production/Stable
Classifier: Intended Audience :: Developers
Classifier: License :: OSI Approved :: BSD License
Classifier: Operating System :: OS Independent
Classifier: Programming Language :: Python
Classifier: Programming Language :: Python :: 2
Classifier: Programming Language :: Python :: 2.7
Classifier: Programming Language :: Python :: 3
Classifier: Programming Language :: Python :: 3.4
Classifier: Programming Language :: Python :: 3.5
Classifier: Programming Language :: Python :: 3.6
Classifier: Programming Language :: Python :: 3.7
Requires-Python: >=2.7, !=3.0.*, !=3.1.*, !=3.2.*, !=3.3.*
Provides-Extra: libcloud
Provides-Extra: sftp
